test.v
module counter(
    input clk,
    input reset,
    output reg [3:0] count
);
    always @(posedge clk or posedge reset) begin
        if (reset)
            count <= 4'b0000;
        else
            count <= count + 1;
    end
endmodule

`timescale 1ns/1ns

module counter_tb;
    reg clk;
    reg reset;
    wire [3:0] count;

    // Instantiate the design
    counter uut (
        .clk(clk),
        .reset(reset),
        .count(count)
    );

    // Clock generation
    initial begin
        clk = 0;
        forever #5 clk = ~clk; // Toggle clock every 5ns
    end

    // Test sequence
    initial begin
        // REQUIRED FOR WAVEFORMS:
        $dumpfile("waves.vcd");      // Name of the output file
        $dumpvars(0, counter_tb);    // Dump all variables in this module

        reset = 1;
        #10;
        reset = 0;
    #100;
        $finish; // Stop simulation
    end
endmodule

waves.vcd
$date
	Sat Nov 29 10:07:21 2025
$end
$version
	Icarus Verilog
$end
$timescale
	1ns
$end
$scope module counter_tb $end
$var wire 4 ! count [3:0] $end
$var reg 1 " clk $end
$var reg 1 # reset $end
$scope module uut $end
$var wire 1 " clk $end
$var wire 1 # reset $end
$var reg 4 $ count [3:0] $end
$upscope $end
$upscope $end
$enddefinitions $end
$comment Show the parameter values. $end
$dumpall
$end
#0
$dumpvars
b0 $
1#
0"
b0 !
$end
#5
1"
#10
0"
0#
#15
b1 !
b1 $
1"
#20
0"
#25
b10 !
b10 $
1"
#30
0"
#35
b11 !
b11 $
1"
#40
0"
#45
b100 !
b100 $
1"
#50
0"
#55
b101 !
b101 $
1"
#60
0"
#65
b110 !
b110 $
1"
#70
0"
#75
b111 !
b111 $
1"
#80
0"
#85
b1000 !
b1000 $
1"
#90
0"
#95
b1001 !
b1001 $
1"
#100
0"
#105
b1010 !
b1010 $
1"
